{
  "name": "tv",
  "maker": "TOSHIBA",
  "modelNumber": "37Z1S",
  "signals": {
    "power":          "8240BF12ED0000",
    "ch1":            "8240BF01FE0000",
    "ch2":            "8240BF02FD0000",
    "ch3":            "8240BF03FC0000",
    "ch4":            "8240BF04FB0000",
    "ch5":            "8240BF05FA0000",
    "ch6":            "8240BF06F90000",
    "ch7":            "8240BF07F80000",
    "ch8":            "8240BF08F70000",
    "ch9":            "8240BF09F60000",
    "ch10":           "8240BF0AF50000",
    "ch11":           "8240BF0BF40000",
    "ch12":           "8240BF0CF30000",
    "switchInput":    "8240BF0FF00000",
    "broadBand":      "8240BF25DA0000",
    "newsRightNow":   "8240BF25DA0000",
    "twoScreen":      "8240BF29D60000",
    "chidigi":        "8240BF7A850000",
    "BS":             "8240BF7C830000",
    "CS":             "8240BF7D820000",
    "channelUp":      "8240BF1BE40000",
    "channelDown":    "8240BF1FE00000",
    "volumeUp":       "8240BF1AE50000",
    "volumeDown":     "8240BF1EE10000",
    "displayScreen":  "8240BF1CE30000",
    "volumeOff":      "8240BF10EF0000",
    "quick":          "8240BF27D80000",
    "regzaLink":      "8240BE34CB0000",
    "tvListings":     "8240BF6E910000",
    "back":           "8240BF3BC40000",
    "finish":         "8240BF3CC30000",
    "doubleUp":       "8240BE20DF0000",
    "doubleDown":     "8240BE21DE0000",
    "doubleLeft":     "8240BE22DD0000",
    "doubleRight":    "8240BE23DC0000",
    "up":             "8240BF3EC10000",
    "down":           "8240BF3FC00000",
    "left":           "8240BF5FA00000",
    "right":          "8240BF5BA40000",
    "ok":             "8240BF3DC20000",
    "blue":           "8240BF738C0000",
    "red":            "8240BF748B0000",
    "green":          "8240BF758A0000",
    "yellow":         "8240BF76890000",
    "dData":          "8243BC14EB0000",
    "recordList":      "8240BE28D70000",
    "miniTvListings": "8240BF77880000",
    "backward":       "8240BE2CD30000",
    "play":           "8240BE2DD20000",
    "forward":        "8240BE2ED10000",
    "fastBackward":   "8240BE27D80000",
    "stop":           "8240BE2BD40000",
    "pause":          "8240BF50AF0000",
    "fastForward":    "8240BE26D90000"
   } 
}
